LICENSE
README.md
setup.py
dvapi/__init__.py
dvapi/main.py
dvapi.egg-info/PKG-INFO
dvapi.egg-info/SOURCES.txt
dvapi.egg-info/dependency_links.txt
dvapi.egg-info/requires.txt
dvapi.egg-info/top_level.txt