Metadata-Version: 2.1
Name: dvapi
Version: 0.0.1
Summary: Interact with your Dataverse
Author: Kasap (Petar Kasapinov)
Author-email: <pkasapinov@otcfin.com>
Keywords: python,api,crud,dataverse
Classifier: Development Status :: 1 - Planning
Classifier: Intended Audience :: Developers
Classifier: Programming Language :: Python :: 3
Classifier: Operating System :: Unix
Classifier: Operating System :: MacOS :: MacOS X
Classifier: Operating System :: Microsoft :: Windows
License-File: LICENSE
